human_id/__init__.py
human_id/cli.py
human_id/dictionary.py
human_id-0.1.0.post3.dist-info/entry_points.txt
human_id-0.1.0.post3.dist-info/WHEEL
human_id-0.1.0.post3.dist-info/METADATA
human_id-0.1.0.post3.dist-info/RECORD
