Metadata-Version: 2.1
Name: human-id
Version: 0.1.0.post3
Summary: Human readable IDs, in Python
Home-page: https://github.com/orf/human_id
License: MIT
Author: Tom Forbes
Author-email: tom@tomforb.es
Requires-Python: >=3.6
Classifier: License :: OSI Approved :: MIT License
Classifier: Programming Language :: Python :: 3
Classifier: Programming Language :: Python :: 3.6
Classifier: Programming Language :: Python :: 3.7
Classifier: Programming Language :: Python :: 3.8
Requires-Dist: click (>=7.1.2,<8.0.0)
Project-URL: Repository, https://github.com/orf/human_id
